{
  "title": "Sad News",
  "author": "verias",
  "date": "05-05-2014",
  "text": "<p>Had a death this weekend, so things are hectic and a bit delayed. Hope you guys enjoy the above. Chrys and Theresa both cosplaying Carol Danvers as Ms Marvel and Captain Marvel respectively.</p>",
  "replies": [
    {
      "author": "David*Guest*",
      "date": "05-05-2014",
      "text": "Understood, Keith. Take what time you need, mate <img src=\"//smilies/smile.gif\" alt=\"Smile\" border=\"0\">"
    },
    {
      "author": "Adamas*Guest*",
      "date": "05-05-2014",
      "text": "Sorry to hear it man. Our wishes are with ya."
    },
    {
      "author": "Gunsolo*Guest*",
      "date": "05-05-2014",
      "text": "Sorry for your loss."
    }
  ]
}